gff_io/__init__.py
gff_io/_reader.py
gff_io/_version.py
gff_io/interval.py
gff_io/test/__init__.py
gff_io/test/examples.tar.gz
gff_io/test/test_reader.py
gff_io-0.0.2.dist-info/LICENSE.md
gff_io-0.0.2.dist-info/METADATA
gff_io-0.0.2.dist-info/WHEEL
gff_io-0.0.2.dist-info/top_level.txt
gff_io-0.0.2.dist-info/zip-safe
gff_io-0.0.2.dist-info/RECORD
